izihawa_langdetect/__init__.py
izihawa_langdetect/_langdetect.py
izihawa_langdetect-1.0.0.dist-info/METADATA
izihawa_langdetect-1.0.0.dist-info/WHEEL
izihawa_langdetect-1.0.0.dist-info/entry_points.txt
izihawa_langdetect-1.0.0.dist-info/RECORD
