Metadata-Version: 2.1
Name: izihawa_langdetect
Version: 1.0.0
Summary: 
Author: Pasha Podolsky
Author-email: ppodolsky@me.com
Requires-Python: >=3.11,<3.12
Classifier: Programming Language :: Python :: 3
Classifier: Programming Language :: Python :: 3.11
Requires-Dist: fasttext-wheel (>=0.9.2,<0.10.0)
